<?xml version='1.0' encoding='utf-8'?>
<tv><channel id="AXN.co">
    <display-name lang="es">AXN</display-name>
    <icon src="http://media.gvp.telefonica.com/storagearea0/IMAGES/00/06/51/6518947_CDE896912C494ADE.png" />
    <icon src="http://media.gvp.telefonica.com/storagearea0/IMAGES/00/06/51/6518947_CDE896912C494ADE.png" />
    <url>http://www.movistar.co</url>
  </channel>
  <programme start="20250117173000 +0000" stop="20250117182000 +0000" channel="AXN.co">
    <title lang="es">NCIS: Los Angeles</title>
    <sub-title lang="es">Exposure</sub-title>
    <desc lang="es">El equipo investiga cuando un reportero de noticias nombra a la gente responsable de una explosión mortal en un evento de caridad patrocinado por los militares.</desc>
    <date>2014</date>
    <episode-num system="onscreen">E23</episode-num>
    <rating system="MJColombia">
      <value>+14</value>
    </rating>
  </programme>
  <programme start="20250117182000 +0000" stop="20250117191000 +0000" channel="AXN.co">
    <title lang="es">CSI</title>
    <sub-title lang="es">Post Mortem</sub-title>
    <desc lang="es">Mientras investiga el asesinato de una anciana, Grissom recibe una réplica en miniatura de la escena del crimen; Greg asiste a una audiencia para aceptar su culpabilidad en la muerte accidental de un adolescente.</desc>
    <date>2006</date>
    <episode-num system="onscreen">E7</episode-num>
    <rating system="MJColombia">
      <value>+14</value>
    </rating>
  </programme>
  <programme start="20250117191000 +0000" stop="20250117200000 +0000" channel="AXN.co">
    <title lang="es">CSI</title>
    <sub-title lang="es">Happenstance</sub-title>
    <desc lang="es">El equipo CSI investiga si los asesinatos de dos mellizos idénticos están relacionados.</desc>
    <date>2006</date>
    <episode-num system="onscreen">E8</episode-num>
    <rating system="MJColombia">
      <value>+14</value>
    </rating>
  </programme>
  <programme start="20250117200000 +0000" stop="20250117205000 +0000" channel="AXN.co">
    <title lang="es">CSI: Miami</title>
    <sub-title lang="es">Bunk</sub-title>
    <desc lang="es">Horatio y Speedle investigan la fabricación de drogas letales en laboratorios móviles; un mujer mayor es asesinada en una casa de retiro.</desc>
    <date>2003</date>
    <episode-num system="onscreen">E13</episode-num>
    <rating system="MJColombia">
      <value>+14</value>
    </rating>
  </programme>
  <programme start="20250117205000 +0000" stop="20250117214000 +0000" channel="AXN.co">
    <title lang="es">CSI: Miami</title>
    <sub-title lang="es">Forced Entry</sub-title>
    <desc lang="es">Un violador en serie es encontrado muerto por sofocación; investigadores examinan los asesinatos del dueño de crematorio y de una chica encontrada detrás de un crematorio.</desc>
    <date>2003</date>
    <episode-num system="onscreen">E14</episode-num>
    <rating system="MJColombia">
      <value>+14</value>
    </rating>
  </programme>
  <programme start="20250117214000 +0000" stop="20250117223000 +0000" channel="AXN.co">
    <title lang="es">Hawaii Five-0</title>
    <sub-title lang="es">Blood Brothers</sub-title>
    <desc lang="es">Varios miembros del equipo caen en una trampa cuando una pista falsa los lleva a investigar un edificio abandonado a punto de explotar. Cuando llegan al inmueble, McGarrett y Danny quedan atrapados en el interior.</desc>
    <date>2014</date>
    <episode-num system="onscreen">E19</episode-num>
    <rating system="MJColombia">
      <value>+14</value>
    </rating>
  </programme>
  <programme start="20250117223000 +0000" stop="20250117232000 +0000" channel="AXN.co">
    <title lang="es">Hawaii Five-0</title>
    <sub-title lang="es">Those Among Us</sub-title>
    <desc lang="es">La investigación de un asesinato devela una posible célula terrorista que planea llevar a cabo un ataque en Estados Unidos.</desc>
    <date>2014</date>
    <episode-num system="onscreen">E20</episode-num>
    <rating system="MJColombia">
      <value>+14</value>
    </rating>
  </programme>
  <programme start="20250117232000 +0000" stop="20250118001000 +0000" channel="AXN.co">
    <title lang="es">Hawaii Five-0</title>
    <sub-title lang="es">Fair Winds and Following Seas</sub-title>
    <desc lang="es">McGarrett y Catherine viajan a Afganistán para impedir que ataquen a un joven cuya familia ella salvó hace unos años atrás.</desc>
    <date>2014</date>
    <episode-num system="onscreen">E21</episode-num>
    <rating system="MJColombia">
      <value>+14</value>
    </rating>
  </programme>
  <programme start="20250118001000 +0000" stop="20250118010500 +0000" channel="AXN.co">
    <title lang="es">CSI: Miami</title>
    <sub-title lang="es">Target Specific</sub-title>
    <desc lang="es">La invasión de una casa se torna en algo más serio cuando el equipo descubre que la mafia rusa está atacándolos.</desc>
    <date>2009</date>
    <episode-num system="onscreen">E19</episode-num>
    <rating system="MJColombia">
      <value>+14</value>
    </rating>
  </programme>
  <programme start="20250118010500 +0000" stop="20250118020000 +0000" channel="AXN.co">
    <title lang="es">CSI: Miami</title>
    <sub-title lang="es">Wolfe in Sheep's Clothing</sub-title>
    <desc lang="es">Ryan es secuestrado y es obligado a traicionar a Horatio y al equipo.</desc>
    <date>2009</date>
    <episode-num system="onscreen">E20</episode-num>
    <rating system="MJColombia">
      <value>+14</value>
    </rating>
  </programme>
  <programme start="20250118020000 +0000" stop="20250118025500 +0000" channel="AXN.co">
    <title lang="es">CSI</title>
    <sub-title lang="es">Working Stiffs</sub-title>
    <desc lang="es">Dos oficinistas planean robar un casino, pero su plan termina cuando el CSI investiga un asesinato.</desc>
    <date>2009</date>
    <episode-num system="onscreen">E3</episode-num>
    <rating system="MJColombia">
      <value>+14</value>
    </rating>
  </programme>
  <programme start="20250118025500 +0000" stop="20250118035000 +0000" channel="AXN.co">
    <title lang="es">CSI</title>
    <sub-title lang="es">Coup de Grace</sub-title>
    <desc lang="es">Un policía mata a otro oficial, por lo que el CSI debe buscar las pruebas para determinar si el tiroteo fue premeditado o un accidente.</desc>
    <date>2009</date>
    <episode-num system="onscreen">E4</episode-num>
    <rating system="MJColombia">
      <value>+14</value>
    </rating>
  </programme>
  <programme start="20250118035000 +0000" stop="20250118044500 +0000" channel="AXN.co">
    <title lang="es">CSI</title>
    <sub-title lang="es">Bloodsport</sub-title>
    <desc lang="es">Un popular entrenador es hallado muerto en su casa y todo el equipo de futbol americano es sospechoso.</desc>
    <date>2009</date>
    <episode-num system="onscreen">E5</episode-num>
    <rating system="MJColombia">
      <value>+14</value>
    </rating>
  </programme>
  <programme start="20250118044500 +0000" stop="20250118053500 +0000" channel="AXN.co">
    <title lang="es">CSI</title>
    <sub-title lang="es">Neverland</sub-title>
    <desc lang="es">Un niño pequeño es encontrado asesinado, por lo que el equipo de CSI descubre evidencia que puede vincular su muerte con un viejo caso que resurgió recientemente.</desc>
    <date>2010</date>
    <episode-num system="onscreen">E15</episode-num>
    <rating system="MJColombia">
      <value>+14</value>
    </rating>
  </programme>
  <programme start="20250118053500 +0000" stop="20250118062500 +0000" channel="AXN.co">
    <title lang="es">CSI: Miami</title>
    <sub-title lang="es">Wet Foot/Dry Foot</sub-title>
    <desc lang="es">Horatio y Megan examinan los restos de un torso humano encontrados en el estómago de un tiburón tigre.</desc>
    <date>2002</date>
    <episode-num system="onscreen">E3</episode-num>
    <rating system="MJColombia">
      <value>+14</value>
    </rating>
  </programme>
  <programme start="20250118062500 +0000" stop="20250118071500 +0000" channel="AXN.co">
    <title lang="es">Hawaii Five-0</title>
    <sub-title lang="es">Nothing More For The Eyes To Search For</sub-title>
    <desc lang="es">En Halloween, Jerry y sus amigos registran el campamento de su niñez buscando evidencia de un asesinato que él presenció de niño; McGarrett investiga a una niña que dibujó la escena de un asesinato antes de que lo descubran.</desc>
    <date>2018</date>
    <episode-num system="onscreen">E5</episode-num>
    <rating system="MJColombia">
      <value>+14</value>
    </rating>
  </programme>
  <programme start="20250118071500 +0000" stop="20250118080500 +0000" channel="AXN.co">
    <title lang="es">CSI</title>
    <sub-title lang="es">Pledging Mr. Johnson</sub-title>
    <desc lang="es">Grissom y Catherine investigan la aparición de una pierna cortada de un cuerpo en un lago. Mientras tanto, Sara y Nick investigan un juramento de fraternidad que ha salido terriblemente mal.</desc>
    <date>2000</date>
    <episode-num system="onscreen">E4</episode-num>
    <rating system="MJColombia">
      <value>+14</value>
    </rating>
  </programme>
  <programme start="20250118080500 +0000" stop="20250118090000 +0000" channel="AXN.co">
    <title lang="es">CSI</title>
    <sub-title lang="es">Friends and Lovers</sub-title>
    <desc lang="es">Grissom y Warrick investigan la muerte de un joven hallado en el desierto; Catherine y Nick investigan la muerte de un decano de la escuela.</desc>
    <date>2000</date>
    <episode-num system="onscreen">E5</episode-num>
    <rating system="MJColombia">
      <value>+14</value>
    </rating>
  </programme>
  <programme start="20250118090000 +0000" stop="20250118100000 +0000" channel="AXN.co">
    <title lang="es">CSI</title>
    <sub-title lang="es">Who Are You?</sub-title>
    <desc lang="es">Grissom y Nick son llamados para identificar a una joven mujer y hallar a su asesino; Warrick y Sara investigan los disparos a un policía.</desc>
    <date>2000</date>
    <episode-num system="onscreen">E6</episode-num>
    <rating system="MJColombia">
      <value>+14</value>
    </rating>
  </programme>
  <programme start="20250118100000 +0000" stop="20250118110000 +0000" channel="AXN.co">
    <title lang="es">CSI</title>
    <sub-title lang="es">Blood Drops</sub-title>
    <desc lang="es">Grissom y el equipo investigan el salvaje asesinato de cuatro miembros de una familia. Inicialmente, parece un extraño crimen perpetrado por una secta, pero el caso se vuelve aún más inquietante cuando descubren el verdadero motivo de la masacre.</desc>
    <date>2000</date>
    <episode-num system="onscreen">E7</episode-num>
    <rating system="MJColombia">
      <value>+14</value>
    </rating>
  </programme>
  <programme start="20250118110000 +0000" stop="20250118120000 +0000" channel="AXN.co">
    <title lang="es">CSI</title>
    <sub-title lang="es">Pledging Mr. Johnson</sub-title>
    <desc lang="es">Grissom y Catherine investigan la aparición de una pierna cortada de un cuerpo en un lago. Mientras tanto, Sara y Nick investigan un juramento de fraternidad que ha salido terriblemente mal.</desc>
    <date>2000</date>
    <episode-num system="onscreen">E4</episode-num>
    <rating system="MJColombia">
      <value>+14</value>
    </rating>
  </programme>
  <programme start="20250118120000 +0000" stop="20250118130000 +0000" channel="AXN.co">
    <title lang="es">CSI</title>
    <sub-title lang="es">Friends and Lovers</sub-title>
    <desc lang="es">Grissom y Warrick investigan la muerte de un joven hallado en el desierto; Catherine y Nick investigan la muerte de un decano de la escuela.</desc>
    <date>2000</date>
    <episode-num system="onscreen">E5</episode-num>
    <rating system="MJColombia">
      <value>+14</value>
    </rating>
  </programme>
  <programme start="20250118130000 +0000" stop="20250118133000 +0000" channel="AXN.co">
    <title lang="es">Tevecompras</title>
    <desc lang="es">Compras por TV donde encuentra los últimos productos del mercado.</desc>
    <date>2009</date>
    <rating system="MJColombia">
      <value>TE</value>
    </rating>
  </programme>
  <programme start="20250118133000 +0000" stop="20250118140000 +0000" channel="AXN.co">
    <title lang="es">Tevecompras</title>
    <desc lang="es">Compras por TV donde encuentra los últimos productos del mercado.</desc>
    <date>2009</date>
    <rating system="MJColombia">
      <value>TE</value>
    </rating>
  </programme>
  <programme start="20250118140000 +0000" stop="20250118143000 +0000" channel="AXN.co">
    <title lang="es">Tevecompras</title>
    <desc lang="es">Compras por TV donde encuentra los últimos productos del mercado.</desc>
    <date>2009</date>
    <rating system="MJColombia">
      <value>TE</value>
    </rating>
  </programme>
  <programme start="20250118143000 +0000" stop="20250118150000 +0000" channel="AXN.co">
    <title lang="es">Tevecompras</title>
    <desc lang="es">Compras por TV donde encuentra los últimos productos del mercado.</desc>
    <date>2009</date>
    <rating system="MJColombia">
      <value>TE</value>
    </rating>
  </programme>
  <programme start="20250118150000 +0000" stop="20250118155000 +0000" channel="AXN.co">
    <title lang="es">CSI</title>
    <sub-title lang="es">Anonymous</sub-title>
    <desc lang="es">Un asesino en serie comienza a dejar pistas para burlarse de Grissom. Warrick y Nick se enfrentan mientras investigan un accidente automovilístico.</desc>
    <date>2000</date>
    <episode-num system="onscreen">E8</episode-num>
    <rating system="MJColombia">
      <value>+14</value>
    </rating>
  </programme>
  <programme start="20250118155000 +0000" stop="20250118164000 +0000" channel="AXN.co">
    <title lang="es">CSI: Miami</title>
    <sub-title lang="es">Fade Out</sub-title>
    <desc lang="es">Las evidencias muestran que una serie de asesinatos están relacionados con el crimen organizado, pero también conducen a Horatio y al equipo a un par de estudiantes de cine cuyo guión refleja los detalles de los crímenes.</desc>
    <date>2006</date>
    <episode-num system="onscreen">E14</episode-num>
    <rating system="MJColombia">
      <value>+14</value>
    </rating>
  </programme>
  <programme start="20250118164000 +0000" stop="20250118173000 +0000" channel="AXN.co">
    <title lang="es">CSI: Miami</title>
    <sub-title lang="es">Skeletons</sub-title>
    <desc lang="es">Cuando un cuerpo es hallado durante un torneo de voleibol, las evidencias llevan a Horatio hasta su némesis, Walter Resden, quien ahora apunta hacia una persona que es protegida por Horatio.</desc>
    <date>2006</date>
    <episode-num system="onscreen">E15</episode-num>
    <rating system="MJColombia">
      <value>+14</value>
    </rating>
  </programme>
  <programme start="20250118173000 +0000" stop="20250118182000 +0000" channel="AXN.co">
    <title lang="es">CSI: Miami</title>
    <sub-title lang="es">Deviant</sub-title>
    <desc lang="es">Investigadores forenses que trabajan en la Florida tratan de esclarecer casos criminales descifrando las pistas por medio de la evidencia para atrapar a los perpetradores.</desc>
    <date>2006</date>
    <episode-num system="onscreen">E16</episode-num>
    <rating system="MJColombia">
      <value>+14</value>
    </rating>
  </programme>
  <programme start="20250118182000 +0000" stop="20250118191000 +0000" channel="AXN.co">
    <title lang="es">Criminal Minds</title>
    <sub-title lang="es">Submerged</sub-title>
    <desc lang="es">Cuando se reporta una serie de homicidios en el patio trasero en California, el equipo de BAU busca a un sujeto desconocido que tiene un pasado desconcertante.</desc>
    <date>2018</date>
    <episode-num system="onscreen">E10</episode-num>
    <rating system="MJColombia">
      <value>+14</value>
    </rating>
  </programme>
  <programme start="20250118191000 +0000" stop="20250118200000 +0000" channel="AXN.co">
    <title lang="es">Criminal Minds</title>
    <sub-title lang="es">Full-Tilt Boogie</sub-title>
    <desc lang="es">El equipo de la UAC investiga el intento de homicidio perpetrado contra la esposa del jefe de policía y descubre un mundo de secretos en un pequeño pueblo de Virginia.</desc>
    <date>2018</date>
    <episode-num system="onscreen">E11</episode-num>
    <rating system="MJColombia">
      <value>+14</value>
    </rating>
  </programme>
  <programme start="20250118200000 +0000" stop="20250118205000 +0000" channel="AXN.co">
    <title lang="es">Criminal Minds</title>
    <sub-title lang="es">Bad moon on the Rise</sub-title>
    <desc lang="es">El BAU es llamado a actuar en Nueva York cuando se reportan varias bajas de carácter brutal en pleno Central Park.</desc>
    <date>2018</date>
    <episode-num system="onscreen">E12</episode-num>
    <rating system="MJColombia">
      <value>+14</value>
    </rating>
  </programme>
  <programme start="20250118205000 +0000" stop="20250118214000 +0000" channel="AXN.co">
    <title lang="es">Criminal Minds</title>
    <sub-title lang="es">Cure</sub-title>
    <desc lang="es">La UAC debe investigar una serie de asesinatos con misteriosos mensajes encontrados en las bocas de cada una de las víctimas.</desc>
    <date>2018</date>
    <episode-num system="onscreen">E13</episode-num>
    <rating system="MJColombia">
      <value>+14</value>
    </rating>
  </programme>
  <programme start="20250118214000 +0000" stop="20250118223000 +0000" channel="AXN.co">
    <title lang="es">Criminal Minds</title>
    <sub-title lang="es">Miasma</sub-title>
    <desc lang="es">La policía de Nueva Orleans encuentra una fosa común en la cripta profanada de un cementerio local. El equipo viaja hasta allá para investigar el hallazgo.</desc>
    <date>2018</date>
    <episode-num system="onscreen">E14</episode-num>
    <rating system="MJColombia">
      <value>+14</value>
    </rating>
  </programme>
  <programme start="20250118223000 +0000" stop="20250118232000 +0000" channel="AXN.co">
    <title lang="es">Criminal Minds</title>
    <sub-title lang="es">Annihilator</sub-title>
    <desc lang="es">El ayudante del director de seguridad nacional del FBI colabora con el equipo en la investigación de un cuádruple homicidio, el asesinato de unos compañeros de piso en San Luis.</desc>
    <date>2018</date>
    <episode-num system="onscreen">E15</episode-num>
    <rating system="MJColombia">
      <value>+14</value>
    </rating>
  </programme>
  <programme start="20250118232000 +0000" stop="20250119001000 +0000" channel="AXN.co">
    <title lang="es">Criminal Minds</title>
    <sub-title lang="es">Last Gasp</sub-title>
    <desc lang="es">El equipo investiga en secreto al sospechoso de haber secuestrado y fotografiado a varias mujeres jóvenes.</desc>
    <date>2018</date>
    <episode-num system="onscreen">E16</episode-num>
    <rating system="MJColombia">
      <value>+14</value>
    </rating>
  </programme>
  <programme start="20250119001000 +0000" stop="20250119010000 +0000" channel="AXN.co">
    <title lang="es">Criminal Minds</title>
    <sub-title lang="es">The Capilanos</sub-title>
    <desc lang="es">La Unidad de Análisis de Conducta debe viajar a Oklahoma para investigar a un payaso asesino que aterroriza a toda la ciudad de Guymon.</desc>
    <date>2018</date>
    <episode-num system="onscreen">E17</episode-num>
    <rating system="MJColombia">
      <value>+14</value>
    </rating>
  </programme>
  <programme start="20250119010000 +0000" stop="20250119015000 +0000" channel="AXN.co">
    <title lang="es">Criminal Minds</title>
    <sub-title lang="es">The Dance of Love</sub-title>
    <desc lang="es">El equipo viaja a Chicago para investigar la identidad de un asesino que deja rosas rojas sobre sus víctimas. Por otra parte, Rossi recibe por sorpresa la visita de su exesposa.</desc>
    <date>2018</date>
    <episode-num system="onscreen">E18</episode-num>
    <rating system="MJColombia">
      <value>+14</value>
    </rating>
  </programme>
  <programme start="20250119015000 +0000" stop="20250119024000 +0000" channel="AXN.co">
    <title lang="es">Criminal Minds</title>
    <sub-title lang="es">Ex Parte</sub-title>
    <desc lang="es">El equipo se hace cargo de una situación de riesgo en la que hay rehenes involucrados en el bufete de abogados donde trabaja la esposa de Matt Simmons.</desc>
    <date>2018</date>
    <episode-num system="onscreen">E19</episode-num>
    <rating system="MJColombia">
      <value>+14</value>
    </rating>
  </programme>
  <programme start="20250119024000 +0000" stop="20250119033000 +0000" channel="AXN.co">
    <title lang="es">Criminal Minds</title>
    <sub-title lang="es">All You Can Eat</sub-title>
    <desc lang="es">El equipo investiga varias muertes sospechosas que tal vez hayan sido provocadas por un ataque terrorista perpetrado con armas biológicas. Mientras tanto, Garcia visita a su hermanastro para ocuparse de un asunto familiar delicado.</desc>
    <date>2018</date>
    <episode-num system="onscreen">E20</episode-num>
    <rating system="MJColombia">
      <value>+14</value>
    </rating>
  </programme>
  <programme start="20250119033000 +0000" stop="20250119042000 +0000" channel="AXN.co">
    <title lang="es">Criminal Minds</title>
    <sub-title lang="es">Mixed Signals</sub-title>
    <desc lang="es">La Unidad de Análisis de Conducta se traslada a Taos, Nuevo México, donde alguien tiene en la mira los lóbulos temporales de sus víctimas.</desc>
    <date>2018</date>
    <episode-num system="onscreen">E21</episode-num>
    <rating system="MJColombia">
      <value>+14</value>
    </rating>
  </programme>
  <programme start="20250119042000 +0000" stop="20250119051000 +0000" channel="AXN.co">
    <title lang="es">Criminal Minds</title>
    <sub-title lang="es">Believer</sub-title>
    <desc lang="es">El equipo cuestiona la credibilidad del extraño relato de un exagente del FBI.</desc>
    <date>2018</date>
    <episode-num system="onscreen">E22</episode-num>
    <rating system="MJColombia">
      <value>+14</value>
    </rating>
  </programme>
  <programme start="20250119051000 +0000" stop="20250119060500 +0000" channel="AXN.co">
    <title lang="es">CSI: Miami</title>
    <sub-title lang="es">Just One Kiss</sub-title>
    <desc lang="es">Una familia adinerada utiliza su poder e influencia para distanciarse de una investigación de violación y asesinato.</desc>
    <date>2002</date>
    <episode-num system="onscreen">E4</episode-num>
    <rating system="MJColombia">
      <value>+14</value>
    </rating>
  </programme>
  <programme start="20250119060500 +0000" stop="20250119070000 +0000" channel="AXN.co">
    <title lang="es">Hawaii Five-0</title>
    <sub-title lang="es">Is Borne On The Back; Is Borne In The Arms</sub-title>
    <desc lang="es">McGarrett cruza una línea prohibida durante la investigación de la muerte de su antiguo compañero de los SEAL, quien murió durante un aterrizaje de emergencia en un portaviones. Adam vuelve a Oahu con malas noticias sobre su matrimonio.</desc>
    <date>2018</date>
    <episode-num system="onscreen">E6</episode-num>
    <rating system="MJColombia">
      <value>+14</value>
    </rating>
  </programme>
  <programme start="20250119070000 +0000" stop="20250119080000 +0000" channel="AXN.co">
    <title lang="es">CSI: NY</title>
    <sub-title lang="es">Heart of Glass</sub-title>
    <desc lang="es">Un magnate de la música es asesinado en su departamento y el único testigo tiene motivo para quererlo muerto.</desc>
    <date>2007</date>
    <episode-num system="onscreen">E16</episode-num>
    <rating system="MJColombia">
      <value>+14</value>
    </rating>
  </programme>
  <programme start="20250119080000 +0000" stop="20250119090000 +0000" channel="AXN.co">
    <title lang="es">CSI: NY</title>
    <sub-title lang="es">The Ride-In</sub-title>
    <desc lang="es">Un hombre llamado Noah es encontrado muerto debajo de una gran cantidad de dinero en efectivo con un arca repleta de personas y animales en su patio trasero.</desc>
    <date>2007</date>
    <episode-num system="onscreen">E17</episode-num>
    <rating system="MJColombia">
      <value>+14</value>
    </rating>
  </programme>
  <programme start="20250119090000 +0000" stop="20250119100000 +0000" channel="AXN.co">
    <title lang="es">CSI: NY</title>
    <sub-title lang="es">Sleight Out of Hand</sub-title>
    <desc lang="es">Investigadores forenses utilizan la ciencia con tecnología de punta para analizar la evidencia y resolver crímenes en la Gran Manzana.</desc>
    <date>2007</date>
    <episode-num system="onscreen">E18</episode-num>
    <rating system="MJColombia">
      <value>+14</value>
    </rating>
  </programme>
  <programme start="20250119100000 +0000" stop="20250119110000 +0000" channel="AXN.co">
    <title lang="es">CSI: NY</title>
    <sub-title lang="es">A Daze of Wine and Roaches</sub-title>
    <desc lang="es">Mac y Stella investigan el homicidio de la cuidadora de una niña, que fue asesinada durante una recaudación de fondos de Naciones Unidas.</desc>
    <date>2007</date>
    <episode-num system="onscreen">E19</episode-num>
    <rating system="MJColombia">
      <value>+14</value>
    </rating>
  </programme>
  <programme start="20250119110000 +0000" stop="20250119120000 +0000" channel="AXN.co">
    <title lang="es">CSI: NY</title>
    <sub-title lang="es">Heart of Glass</sub-title>
    <desc lang="es">Un magnate de la música es asesinado en su departamento y el único testigo tiene motivo para quererlo muerto.</desc>
    <date>2007</date>
    <episode-num system="onscreen">E16</episode-num>
    <rating system="MJColombia">
      <value>+14</value>
    </rating>
  </programme>
  <programme start="20250119120000 +0000" stop="20250119130000 +0000" channel="AXN.co">
    <title lang="es">CSI: NY</title>
    <sub-title lang="es">The Ride-In</sub-title>
    <desc lang="es">Un hombre llamado Noah es encontrado muerto debajo de una gran cantidad de dinero en efectivo con un arca repleta de personas y animales en su patio trasero.</desc>
    <date>2007</date>
    <episode-num system="onscreen">E17</episode-num>
    <rating system="MJColombia">
      <value>+14</value>
    </rating>
  </programme>
  <programme start="20250119130000 +0000" stop="20250119133000 +0000" channel="AXN.co">
    <title lang="es">Tevecompras</title>
    <desc lang="es">Compras por TV donde encuentra los últimos productos del mercado.</desc>
    <date>2009</date>
    <rating system="MJColombia">
      <value>TE</value>
    </rating>
  </programme>
  <programme start="20250119133000 +0000" stop="20250119140000 +0000" channel="AXN.co">
    <title lang="es">Tevecompras</title>
    <desc lang="es">Compras por TV donde encuentra los últimos productos del mercado.</desc>
    <date>2009</date>
    <rating system="MJColombia">
      <value>TE</value>
    </rating>
  </programme>
  <programme start="20250119140000 +0000" stop="20250119143000 +0000" channel="AXN.co">
    <title lang="es">Tevecompras</title>
    <desc lang="es">Compras por TV donde encuentra los últimos productos del mercado.</desc>
    <date>2009</date>
    <rating system="MJColombia">
      <value>TE</value>
    </rating>
  </programme>
  <programme start="20250119143000 +0000" stop="20250119150000 +0000" channel="AXN.co">
    <title lang="es">Tevecompras</title>
    <desc lang="es">Compras por TV donde encuentra los últimos productos del mercado.</desc>
    <date>2009</date>
    <rating system="MJColombia">
      <value>TE</value>
    </rating>
  </programme>
  <programme start="20250119150000 +0000" stop="20250119155000 +0000" channel="AXN.co">
    <title lang="es">NCIS: Los Angeles</title>
    <sub-title lang="es">Deliverance</sub-title>
    <desc lang="es">Hetty y el equipo de NCIS siguen buscando un libro, lo que atrae la atención de varias agencias de seguridad extranjeras.</desc>
    <date>2010</date>
    <episode-num system="onscreen">E10</episode-num>
    <rating system="MJColombia">
      <value>+14</value>
    </rating>
  </programme>
  <programme start="20250119155000 +0000" stop="20250119164000 +0000" channel="AXN.co">
    <title lang="es">NCIS: Los Angeles</title>
    <sub-title lang="es">Disorder</sub-title>
    <desc lang="es">Kensi se relaciona personalmente con un oficial de la inteligencia naval que sufre de estrés postraumático y que es el único sobreviviente de un conflicto mortal investigado por el equipo de NCIS.</desc>
    <date>2010</date>
    <episode-num system="onscreen">E11</episode-num>
    <rating system="MJColombia">
      <value>+14</value>
    </rating>
  </programme>
  <programme start="20250119164000 +0000" stop="20250119173500 +0000" channel="AXN.co">
    <title lang="es">NCIS: Criminología Naval</title>
    <sub-title lang="es">The Weak Link</sub-title>
    <desc lang="es">Gibbs y su equipo creen que la muerte accidental de un miembro de la Marina, durante un ejercicio de rutina, fue un asesinato.</desc>
    <date>2004</date>
    <episode-num system="onscreen">E22</episode-num>
    <rating system="MJColombia">
      <value>+14</value>
    </rating>
  </programme>
  <programme start="20250119173500 +0000" stop="20250119183000 +0000" channel="AXN.co">
    <title lang="es">NCIS: Criminología Naval</title>
    <sub-title lang="es">Reveille</sub-title>
    <desc lang="es">Gibbs finalmente se enfrenta con Ari, el terrorista del Bete Noir quien lo había herido antes de escapar.</desc>
    <date>2004</date>
    <episode-num system="onscreen">E23</episode-num>
    <rating system="MJColombia">
      <value>+14</value>
    </rating>
  </programme>
  <programme start="20250119183000 +0000" stop="20250119192500 +0000" channel="AXN.co">
    <title lang="es">NCIS: Criminología Naval</title>
    <sub-title lang="es">See No Evil</sub-title>
    <desc lang="es">Gibbs y su equipo se enfrentan a un reto cuando la esposa e hija invidente de nueve años de un capitán de la Armada son secuestradas en su casa, y el capitán es secuestrado en su propia oficina.</desc>
    <date>2004</date>
    <episode-num system="onscreen">E1</episode-num>
    <rating system="MJColombia">
      <value>+14</value>
    </rating>
  </programme>
  <programme start="20250119192500 +0000" stop="20250119201500 +0000" channel="AXN.co">
    <title lang="es">Criminal Minds</title>
    <sub-title lang="es">The Big Game</sub-title>
    <desc lang="es">El equipo de BAU investiga el asesinato de una adinerada pareja en su casa después ver el Super Bowl. Alguien llama al servicio de emergencias citando pasajes de la Biblia segundos antes de producirse los asesinatos.</desc>
    <date>2007</date>
    <episode-num system="onscreen">E14</episode-num>
    <rating system="MJColombia">
      <value>+14</value>
    </rating>
  </programme>
  <programme start="20250119201500 +0000" stop="20250119211000 +0000" channel="AXN.co">
    <title lang="es">Criminal Minds</title>
    <sub-title lang="es">Revelations</sub-title>
    <desc lang="es">Un equipo élite de investigadores del FBI analiza las mentes criminales más enfermas del país.</desc>
    <date>2007</date>
    <episode-num system="onscreen">E15</episode-num>
    <rating system="MJColombia">
      <value>+14</value>
    </rating>
  </programme>
  <programme start="20250119211000 +0000" stop="20250119220500 +0000" channel="AXN.co">
    <title lang="es">Criminal Minds</title>
    <sub-title lang="es">Fear and Loathing</sub-title>
    <desc lang="es">El equipo de BAU viaja a un vecindario elegante de Nueva York para cazar a un posible asesino en serie motivado racialmente antes de que las consecuencias de los delitos lleve a problemas más grandes.</desc>
    <date>2007</date>
    <episode-num system="onscreen">E16</episode-num>
    <rating system="MJColombia">
      <value>+14</value>
    </rating>
  </programme>
  <programme start="20250119220500 +0000" stop="20250119225500 +0000" channel="AXN.co">
    <title lang="es">Criminal Minds</title>
    <sub-title lang="es">Distress</sub-title>
    <desc lang="es">El equipo viaja a Houston para investigar una serie de asesinatos aparentemente arbitrarios en obras de construcción; el equipo nota un cambio distinto del comportamiento de Reid.</desc>
    <date>2007</date>
    <episode-num system="onscreen">E17</episode-num>
    <rating system="MJColombia">
      <value>+14</value>
    </rating>
  </programme>
  <programme start="20250119225500 +0000" stop="20250119234500 +0000" channel="AXN.co">
    <title lang="es">Criminal Minds</title>
    <sub-title lang="es">Jones</sub-title>
    <desc lang="es">El equipo viaja a Nueva Orleans para detener a un asesino en serie que ha vuelto a matar, tras un receso de 15 meses. Entretanto, Reid intenta superar el trauma que le creó haber sido secuestrado y torturado por un asesino en serie.</desc>
    <date>2007</date>
    <episode-num system="onscreen">E18</episode-num>
    <rating system="MJColombia">
      <value>+14</value>
    </rating>
  </programme>
  <programme start="20250119234500 +0000" stop="20250120003500 +0000" channel="AXN.co">
    <title lang="es">CSI: Miami</title>
    <sub-title lang="es">Blood Lust</sub-title>
    <desc lang="es">Después de que una mujer apenas logra escapar de las manos de un asesino en serie, Horatio intenta atrapar al criminal.</desc>
    <date>2011</date>
    <episode-num system="onscreen">E15</episode-num>
    <rating system="MJColombia">
      <value>+14</value>
    </rating>
  </programme>
  <programme start="20250120003500 +0000" stop="20250120012500 +0000" channel="AXN.co">
    <title lang="es">CSI: Miami</title>
    <sub-title lang="es">Hunting Ground</sub-title>
    <desc lang="es">El equipo descubre un club en donde los cazadores persiguen a presas humanos.</desc>
    <date>2011</date>
    <episode-num system="onscreen">E16</episode-num>
    <rating system="MJColombia">
      <value>+14</value>
    </rating>
  </programme>
  <programme start="20250120012500 +0000" stop="20250120021500 +0000" channel="AXN.co">
    <title lang="es">CSI: Miami</title>
    <sub-title lang="es">Special Delivery</sub-title>
    <desc lang="es">El equipo intenta encontrar una conexión entre los asesinatos de un camionero y una mujer en su ruta de reparto.</desc>
    <date>2011</date>
    <episode-num system="onscreen">E17</episode-num>
    <rating system="MJColombia">
      <value>+14</value>
    </rating>
  </programme>
  <programme start="20250120021500 +0000" stop="20250120030500 +0000" channel="AXN.co">
    <title lang="es">CSI: Miami</title>
    <sub-title lang="es">About Face</sub-title>
    <desc lang="es">Un prófugo toma a Natalia de rehén y revela secretos espantosos sobre sus crímenes.</desc>
    <date>2011</date>
    <episode-num system="onscreen">E18</episode-num>
    <rating system="MJColombia">
      <value>+14</value>
    </rating>
  </programme>
  <programme start="20250120030500 +0000" stop="20250120035500 +0000" channel="AXN.co">
    <title lang="es">CSI: Miami</title>
    <sub-title lang="es">Caged</sub-title>
    <desc lang="es">Horatio protege un artista marcial de su hermano escapado del cárcel.</desc>
    <date>2011</date>
    <episode-num system="onscreen">E19</episode-num>
    <rating system="MJColombia">
      <value>+14</value>
    </rating>
  </programme>
  <programme start="20250120035500 +0000" stop="20250120044500 +0000" channel="AXN.co">
    <title lang="es">CSI: Miami</title>
    <sub-title lang="es">Paint It Black</sub-title>
    <desc lang="es">El cuerpo de un estudiante universitario se encuentra en un jacuzi.</desc>
    <date>2011</date>
    <episode-num system="onscreen">E20</episode-num>
    <rating system="MJColombia">
      <value>+14</value>
    </rating>
  </programme>
  <programme start="20250120044500 +0000" stop="20250120053500 +0000" channel="AXN.co">
    <title lang="es">CSI</title>
    <sub-title lang="es">Irradiator</sub-title>
    <desc lang="es">La investigación de Langston del asesinato de una familia lo acerca cada vez más a la captura de un asesino en serie.</desc>
    <date>2010</date>
    <episode-num system="onscreen">E17</episode-num>
    <rating system="MJColombia">
      <value>+14</value>
    </rating>
  </programme>
  <programme start="20250120053500 +0000" stop="20250120062500 +0000" channel="AXN.co">
    <title lang="es">CSI: Miami</title>
    <sub-title lang="es">Ashes to Ashes</sub-title>
    <desc lang="es">Un sacerdote es asesinado en la rectoría de su iglesia. Horatio y Delko examinan los restos carbonizados de una mujer embarazada.</desc>
    <date>2002</date>
    <episode-num system="onscreen">E5</episode-num>
    <rating system="MJColombia">
      <value>+14</value>
    </rating>
  </programme>
  <programme start="20250120062500 +0000" stop="20250120071500 +0000" channel="AXN.co">
    <title lang="es">Hawaii Five-0</title>
    <sub-title lang="es">The Smoke Seen in the Dream Now Rises</sub-title>
    <desc lang="es">McGarrett investiga un caso de la década de 1940 que quedó sin resolver, en el que trabajaron su abuelo y el famoso detective de Honolulú Chang Apana. Además, McGarrett y Danny preparan la apertura de su restaurante.</desc>
    <date>2018</date>
    <episode-num system="onscreen">E7</episode-num>
    <rating system="MJColombia">
      <value>+14</value>
    </rating>
  </programme>
  <programme start="20250120071500 +0000" stop="20250120080500 +0000" channel="AXN.co">
    <title lang="es">NCIS: Los Angeles</title>
    <sub-title lang="es">Paper Soldiers</sub-title>
    <desc lang="es">La viuda de un infante de marina es sospechosa de la muerte de su marido, Sam y Callen ayudan a determinar si ha habido un encubrimiento.</desc>
    <date>2013</date>
    <episode-num system="onscreen">E12</episode-num>
    <rating system="MJColombia">
      <value>+14</value>
    </rating>
  </programme>
  <programme start="20250120080500 +0000" stop="20250120090000 +0000" channel="AXN.co">
    <title lang="es">NCIS: Los Angeles</title>
    <sub-title lang="es">The Chosen One</sub-title>
    <desc lang="es">Callen debe infiltrarse en una red de terroristas que planean su siguiente ataque contra los EE.UU.</desc>
    <date>2013</date>
    <episode-num system="onscreen">E13</episode-num>
    <rating system="MJColombia">
      <value>+14</value>
    </rating>
  </programme>
  <programme start="20250120090000 +0000" stop="20250120100000 +0000" channel="AXN.co">
    <title lang="es">NCIS: Los Angeles</title>
    <sub-title lang="es">Kill House</sub-title>
    <desc lang="es">El equipo NCIS irá de incógnito como una fuerza de élite con el fin de investigar a un capo de un cartel con conexiones terroristas.</desc>
    <date>2013</date>
    <episode-num system="onscreen">E14</episode-num>
    <rating system="MJColombia">
      <value>+14</value>
    </rating>
  </programme>
  <programme start="20250120100000 +0000" stop="20250120110000 +0000" channel="AXN.co">
    <title lang="es">NCIS: Los Angeles</title>
    <sub-title lang="es">History</sub-title>
    <desc lang="es">El equipo interroga el único superviviente de una banda de terroristas.</desc>
    <date>2013</date>
    <episode-num system="onscreen">E15</episode-num>
    <rating system="MJColombia">
      <value>+14</value>
    </rating>
  </programme>
  <programme start="20250120110000 +0000" stop="20250120120000 +0000" channel="AXN.co">
    <title lang="es">NCIS: Los Angeles</title>
    <sub-title lang="es">Paper Soldiers</sub-title>
    <desc lang="es">La viuda de un infante de marina es sospechosa de la muerte de su marido, Sam y Callen ayudan a determinar si ha habido un encubrimiento.</desc>
    <date>2013</date>
    <episode-num system="onscreen">E12</episode-num>
    <rating system="MJColombia">
      <value>+14</value>
    </rating>
  </programme>
  <programme start="20250120120000 +0000" stop="20250120130000 +0000" channel="AXN.co">
    <title lang="es">NCIS: Los Angeles</title>
    <sub-title lang="es">The Chosen One</sub-title>
    <desc lang="es">Callen debe infiltrarse en una red de terroristas que planean su siguiente ataque contra los EE.UU.</desc>
    <date>2013</date>
    <episode-num system="onscreen">E13</episode-num>
    <rating system="MJColombia">
      <value>+14</value>
    </rating>
  </programme>
  <programme start="20250120130000 +0000" stop="20250120133000 +0000" channel="AXN.co">
    <title lang="es">Tevecompras</title>
    <desc lang="es">Compras por TV donde encuentra los últimos productos del mercado.</desc>
    <date>2009</date>
    <rating system="MJColombia">
      <value>TE</value>
    </rating>
  </programme>
  <programme start="20250120133000 +0000" stop="20250120140000 +0000" channel="AXN.co">
    <title lang="es">Tevecompras</title>
    <desc lang="es">Compras por TV donde encuentra los últimos productos del mercado.</desc>
    <date>2009</date>
    <rating system="MJColombia">
      <value>TE</value>
    </rating>
  </programme>
  <programme start="20250120140000 +0000" stop="20250120143000 +0000" channel="AXN.co">
    <title lang="es">Tevecompras</title>
    <desc lang="es">Compras por TV donde encuentra los últimos productos del mercado.</desc>
    <date>2009</date>
    <rating system="MJColombia">
      <value>TE</value>
    </rating>
  </programme>
  <programme start="20250120143000 +0000" stop="20250120150000 +0000" channel="AXN.co">
    <title lang="es">Tevecompras</title>
    <desc lang="es">Compras por TV donde encuentra los últimos productos del mercado.</desc>
    <date>2009</date>
    <rating system="MJColombia">
      <value>TE</value>
    </rating>
  </programme>
  <programme start="20250120150000 +0000" stop="20250120155000 +0000" channel="AXN.co">
    <title lang="es">Criminal Minds</title>
    <sub-title lang="es">Blood Hungry</sub-title>
    <desc lang="es">Hotchner y su equipo intentan meterse en la mente de un asesino psicópata cuyas fantasías lo llevan a matar.</desc>
    <date>2005</date>
    <episode-num system="onscreen">E11</episode-num>
    <rating system="MJColombia">
      <value>+14</value>
    </rating>
  </programme>
  <programme start="20250120155000 +0000" stop="20250120164000 +0000" channel="AXN.co">
    <title lang="es">Criminal Minds</title>
    <sub-title lang="es">What Fresh Hell?</sub-title>
    <desc lang="es">La coartada del padre de una niña secuestrada lo absuelve de toda sospecha, y los investigadores buscan pistas en el aparentemente seguro vecindario para encontrar al responsable.</desc>
    <date>2006</date>
    <episode-num system="onscreen">E12</episode-num>
    <rating system="MJColombia">
      <value>+14</value>
    </rating>
  </programme>
  <programme start="20250120164000 +0000" stop="20250120173000 +0000" channel="AXN.co">
    <title lang="es">NCIS: Criminología Naval</title>
    <sub-title lang="es">Grace Period</sub-title>
    <desc lang="es">Cassidy (Jessica Steen) blames herself when the team learns that a tip on terrorist activity was a trap that resulted in the deaths of two agents.</desc>
    <date>2007</date>
    <episode-num system="onscreen">E19</episode-num>
    <rating system="MJColombia">
      <value>+14</value>
    </rating>
  </programme>
  <programme start="20250120173000 +0000" stop="20250120182000 +0000" channel="AXN.co">
    <title lang="es">NCIS: Los Angeles</title>
    <sub-title lang="es">Deep Trouble</sub-title>
    <desc lang="es">El equipo descubre el plan del cartel para transportar cocaína a los EE.UU. desde Colombia usando un submarino; Hetty debe ir a Whashington.</desc>
    <date>2014</date>
    <episode-num system="onscreen">E24</episode-num>
    <rating system="MJColombia">
      <value>+14</value>
    </rating>
  </programme>
  <programme start="20250120182000 +0000" stop="20250120191000 +0000" channel="AXN.co">
    <title lang="es">CSI</title>
    <sub-title lang="es">Living Legend</sub-title>
    <desc lang="es">Grissom y su equipo investigan una serie de asesinatos en Las Vegas que podrían estar relacionados con un infame jefe de la mafia de los años 70, que desapareció hace muchos años.</desc>
    <date>2006</date>
    <episode-num system="onscreen">E9</episode-num>
    <rating system="MJColombia">
      <value>+14</value>
    </rating>
  </programme>
  <programme start="20250120191000 +0000" stop="20250120200000 +0000" channel="AXN.co">
    <title lang="es">CSI</title>
    <sub-title lang="es">Loco Motives</sub-title>
    <desc lang="es">Un asesinato en una planta de manufactura avícola conduce al equipo de CSI a descubrir la identidad de un asesino en serie que deja réplicas en miniatura de sus escenas del crimen.</desc>
    <date>2006</date>
    <episode-num system="onscreen">E10</episode-num>
    <rating system="MJColombia">
      <value>+14</value>
    </rating>
  </programme>
  <programme start="20250120200000 +0000" stop="20250120205000 +0000" channel="AXN.co">
    <title lang="es">CSI: Miami</title>
    <sub-title lang="es">Dead Woman Walking</sub-title>
    <desc lang="es">Un asesinato expone a Horatio y a algunos en su equipo a ser expuesto a una radiación muy peligrosa, y esto los lleva a donde un abogado que esta muriendo debido a esto.</desc>
    <date>2003</date>
    <episode-num system="onscreen">E15</episode-num>
    <rating system="MJColombia">
      <value>+14</value>
    </rating>
  </programme>
  <programme start="20250120205000 +0000" stop="20250120214000 +0000" channel="AXN.co">
    <title lang="es">CSI: Miami</title>
    <sub-title lang="es">Evidence of Things Unseen</sub-title>
    <desc lang="es">El equipo investiga el asesinato de un hombre encontrado acuchillado, en la cabina de un espectáculo erótico.</desc>
    <date>2003</date>
    <episode-num system="onscreen">E16</episode-num>
    <rating system="MJColombia">
      <value>+14</value>
    </rating>
  </programme>
  <programme start="20250120214000 +0000" stop="20250120223000 +0000" channel="AXN.co">
    <title lang="es">Hawaii Five-0</title>
    <sub-title lang="es">Family Comes First</sub-title>
    <desc lang="es">Grover se ve obligado a robar 100 millones de dólares cuando un enemigo secuestra a su hija. Wo Fat se dirige a Oahu después de escapar de la prisión.</desc>
    <date>2014</date>
    <episode-num system="onscreen">E22</episode-num>
    <rating system="MJColombia">
      <value>+14</value>
    </rating>
  </programme>
  <programme start="20250120223000 +0000" stop="20250120232000 +0000" channel="AXN.co">
    <title lang="es">Hawaii Five-0</title>
    <sub-title lang="es">Nowhere To Hide</sub-title>
    <desc lang="es">El equipo busca a un terrorista en Oahu con un vehículo aéreo no tripulado convertido en un arma. McGarrett y Danno van a una revisión con un psicólogo.</desc>
    <date>2014</date>
    <episode-num system="onscreen">E1</episode-num>
    <rating system="MJColombia">
      <value>+14</value>
    </rating>
  </programme>
  <programme start="20250120232000 +0000" stop="20250121001000 +0000" channel="AXN.co">
    <title lang="es">Hawaii Five-0</title>
    <sub-title lang="es">Family Man</sub-title>
    <desc lang="es">La hija pequeña de un SEAL de la Marina de los Estados Unidos es secuestrada, pero el equipo descubre que los secuestradores se equivocaron de chica y están negociando con la familia equivocada.</desc>
    <date>2014</date>
    <episode-num system="onscreen">E2</episode-num>
    <rating system="MJColombia">
      <value>+14</value>
    </rating>
  </programme>
  <channel id="AXN.(Axn).pe">
    <display-name lang="es">AXN (Axn)</display-name>
    <icon src="http://media.gvp.telefonica.com/storagearea0/IMAGES/00/06/51/6518947_CDE896912C494ADE.png" />
    <url>http://www.movistar.com.pe</url>
  </channel>
  <channel id="AXN.HD.(AXNHD).pe">
    <display-name lang="es">AXN HD (AXNHD)</display-name>
    <icon src="http://media.gvp.telefonica.com/storagearea0/IMAGES/00/06/51/6518947_CDE896912C494ADE.png" />
    <url>http://www.movistar.com.pe</url>
  </channel>
  </tv>